simple_hifigan/__init__.py
simple_hifigan/models.py
simple_hifigan/data/config.json
simple_hifigan/data/generator_LJSpeech.pth.tar
simple_hifigan/data/generator_universal.pth.tar
simple_hifigan-0.1.1.dist-info/METADATA
simple_hifigan-0.1.1.dist-info/WHEEL
simple_hifigan-0.1.1.dist-info/top_level.txt
simple_hifigan-0.1.1.dist-info/RECORD
